drb_impl_wms/__init__.py
drb_impl_wms/_version.py
drb_impl_wms/cache.py
drb_impl_wms/cortex.yml
drb_impl_wms/exceptions.py
drb_impl_wms/factory.py
drb_impl_wms/wms_nodes.py
drb_impl_wms-1.0.0.data/data/requirements.txt
drb_impl_wms-1.0.0.dist-info/METADATA
drb_impl_wms-1.0.0.dist-info/WHEEL
drb_impl_wms-1.0.0.dist-info/entry_points.txt
drb_impl_wms-1.0.0.dist-info/top_level.txt
drb_impl_wms-1.0.0.dist-info/RECORD
